iotronicclient/__init__.py
iotronicclient/client.py
iotronicclient/exc.py
iotronicclient/shell.py
iotronicclient/common/__init__.py
iotronicclient/common/base.py
iotronicclient/common/cliutils.py
iotronicclient/common/filecache.py
iotronicclient/common/http.py
iotronicclient/common/i18n.py
iotronicclient/common/utils.py
iotronicclient/common/apiclient/__init__.py
iotronicclient/common/apiclient/base.py
iotronicclient/common/apiclient/exceptions.py
iotronicclient/v1/__init__.py
iotronicclient/v1/board.py
iotronicclient/v1/board_shell.py
iotronicclient/v1/client.py
iotronicclient/v1/exposed_service.py
iotronicclient/v1/exposed_service_shell.py
iotronicclient/v1/fleet.py
iotronicclient/v1/fleet_shell.py
iotronicclient/v1/plugin.py
iotronicclient/v1/plugin_injection.py
iotronicclient/v1/plugin_injection_shell.py
iotronicclient/v1/plugin_shell.py
iotronicclient/v1/port.py
iotronicclient/v1/port_shell.py
iotronicclient/v1/resource_fields.py
iotronicclient/v1/service.py
iotronicclient/v1/service_shell.py
iotronicclient/v1/shell.py
iotronicclient/v1/utils.py
iotronicclient/v1/webservice.py
iotronicclient/v1/webservice_shell.py
python_iotronicclient-0.4.7.dist-info/AUTHORS
python_iotronicclient-0.4.7.dist-info/LICENSE
python_iotronicclient-0.4.7.dist-info/METADATA
python_iotronicclient-0.4.7.dist-info/WHEEL
python_iotronicclient-0.4.7.dist-info/entry_points.txt
python_iotronicclient-0.4.7.dist-info/pbr.json
python_iotronicclient-0.4.7.dist-info/top_level.txt
python_iotronicclient-0.4.7.dist-info/RECORD
